calculate/__init__.py
add_soham-0.0.1.dist-info/LICENSE.txt
add_soham-0.0.1.dist-info/METADATA
add_soham-0.0.1.dist-info/WHEEL
add_soham-0.0.1.dist-info/top_level.txt
add_soham-0.0.1.dist-info/RECORD
