Metadata-Version: 2.1
Name: add-soham
Version: 0.0.1
Summary: This is a Program which can add stuff
Home-page: UNKNOWN
Author: Soham Das
Author-email: d.somamdas9@gmail.com
License: UNKNOWN
Platform: UNKNOWN
Classifier: Programming Language :: Python :: 3
Classifier: License :: OSI Approved :: MIT License
Classifier: Operating System :: OS Independent
